datasentinel/__init__.py
datasentinel/core.py
datasentinel/notification/__init__.py
datasentinel/notification/notifier/__init__.py
datasentinel/notification/notifier/core.py
datasentinel/notification/notifier/manager.py
datasentinel/notification/notifier/email/__init__.py
datasentinel/notification/notifier/email/smtp_email_notifier.py
datasentinel/notification/notifier/slack/__init__.py
datasentinel/notification/notifier/slack/slack_notifier.py
datasentinel/notification/renderer/__init__.py
datasentinel/notification/renderer/core.py
datasentinel/notification/renderer/email/__init__.py
datasentinel/notification/renderer/email/template_email_message_renderer.py
datasentinel/notification/renderer/email/templates/default.html
datasentinel/notification/renderer/slack/__init__.py
datasentinel/notification/renderer/slack/slack_message_renderer.py
datasentinel/session/__init__.py
datasentinel/session/core.py
datasentinel/session/data_sentinel_session.py
datasentinel/store/__init__.py
datasentinel/store/audit/__init__.py
datasentinel/store/audit/core.py
datasentinel/store/audit/manager.py
datasentinel/store/audit/row.py
datasentinel/store/audit/database/__init__.py
datasentinel/store/audit/database/database_audit_store.py
datasentinel/store/audit/spark/__init__.py
datasentinel/store/audit/spark/deltatable_audit_store.py
datasentinel/store/result/__init__.py
datasentinel/store/result/core.py
datasentinel/store/result/manager.py
datasentinel/store/result/spark/__init__.py
datasentinel/store/result/spark/deltatable_result_store.py
datasentinel/store/utils/__init__.py
datasentinel/store/utils/deltatable_appender.py
datasentinel/store/utils/spark_utils.py
datasentinel/validation/__init__.py
datasentinel/validation/core.py
datasentinel/validation/data_validation.py
datasentinel/validation/result.py
datasentinel/validation/status.py
datasentinel/validation/workflow.py
datasentinel/validation/check/__init__.py
datasentinel/validation/check/core.py
datasentinel-0.2.0.dist-info/licenses/LICENSE
datasentinel-0.2.0.dist-info/METADATA
datasentinel-0.2.0.dist-info/WHEEL
datasentinel-0.2.0.dist-info/top_level.txt
datasentinel-0.2.0.dist-info/RECORD
